{
  "basepath": "/",
  "url": "https://devfest19indore.firebaseapp.com/",
  "analytics": "UA-43643469-8",
  "prefix": "/",
  "firebase": {
    "apiKey": "AIzaSyDpnH74-sRbVI3mOA3MvdxBPeOWwqgJeVQ",
    "authDomain": "devfest19indore.firebaseapp.com",
    "databaseURL": "https://devfest19indore.firebaseio.com",
    "projectId": "devfest19indore",
    "storageBucket": "",
    "messagingSenderId": "59387412033",
    "appId": "1:59387412033:web:f2a79f7d99bf3a94"
  },
  "googleMapApiKey": "AIzaSyDWy6O98n-ueoVaYPWRPve23vjm3JP08gw"
}
